{
  "main": {
    "id": "39133ef2f6059ad0",
    "type": "split",
    "children": [
      {
        "id": "47bc5f2e71d864d0",
        "type": "tabs",
        "children": [
          {
            "id": "b04aa7190fba4dd8",
            "type": "leaf",
            "state": {
              "type": "markdown",
              "state": {
                "file": "projects/HeadteacherChat (Work in Progress).md",
                "mode": "source",
                "source": false
              }
            }
          }
        ]
      }
    ],
    "direction": "vertical"
  },
  "left": {
    "id": "572c697db0123378",
    "type": "split",
    "children": [
      {
        "id": "e79ea17f28ad9eb4",
        "type": "tabs",
        "children": [
          {
            "id": "3cedc74c45ab40e1",
            "type": "leaf",
            "state": {
              "type": "file-explorer",
              "state": {
                "sortOrder": "alphabetical"
              }
            }
          },
          {
            "id": "af4eba27ca6eb1ac",
            "type": "leaf",
            "state": {
              "type": "search",
              "state": {
                "query": "",
                "matchingCase": false,
                "explainSearch": false,
                "collapseAll": false,
                "extraContext": false,
                "sortOrder": "alphabetical"
              }
            }
          },
          {
            "id": "554404122bb6c337",
            "type": "leaf",
            "state": {
              "type": "starred",
              "state": {}
            }
          }
        ]
      }
    ],
    "direction": "horizontal",
    "width": 300
  },
  "right": {
    "id": "5fd01e177d006b53",
    "type": "split",
    "children": [
      {
        "id": "cdca0a7be1de5ea3",
        "type": "tabs",
        "children": [
          {
            "id": "6aa32338f07b722b",
            "type": "leaf",
            "state": {
              "type": "backlink",
              "state": {
                "file": "projects/HeadteacherChat (Work in Progress).md",
                "collapseAll": false,
                "extraContext": false,
                "sortOrder": "alphabetical",
                "showSearch": false,
                "searchQuery": "",
                "backlinkCollapsed": false,
                "unlinkedCollapsed": true
              }
            }
          },
          {
            "id": "a7ecf6f04e580409",
            "type": "leaf",
            "state": {
              "type": "outgoing-link",
              "state": {
                "file": "projects/HeadteacherChat (Work in Progress).md",
                "linksCollapsed": false,
                "unlinkedCollapsed": true
              }
            }
          },
          {
            "id": "d3237723a1ce3c7a",
            "type": "leaf",
            "state": {
              "type": "tag",
              "state": {
                "sortOrder": "frequency",
                "useHierarchy": true
              }
            }
          },
          {
            "id": "f5590a77fc764078",
            "type": "leaf",
            "state": {
              "type": "outline",
              "state": {
                "file": "projects/HeadteacherChat (Work in Progress).md"
              }
            }
          }
        ]
      }
    ],
    "direction": "horizontal",
    "width": 300,
    "collapsed": true
  },
  "left-ribbon": {
    "hiddenItems": {
      "markdown-importer:Open format converter": false,
      "switcher:Open quick switcher": false,
      "graph:Open graph view": false,
      "canvas:Create new canvas": false,
      "daily-notes:Open today's daily note": false,
      "templates:Insert template": false,
      "command-palette:Open command palette": false
    }
  },
  "active": "b04aa7190fba4dd8",
  "lastOpenFiles": [
    "projects/Stay-project.md",
    "index.md",
    "projects/HeadteacherChat (Work in Progress).md",
    "projects/Refresh of HeadteacherChat Shop.md",
    "media/icon-htchat.png",
    "media/icon-htchat.png.png",
    "projects/scribe-project.md",
    "media/icon-stay.png",
    "media/Frame 43.png",
    "projects/2023 Headteacher Planner.md",
    "posts/coming-soon.md",
    "media/joao-vitor-duarte-k4Lt0CjUnb0-unsplash 2.jpeg",
    "Untitled.md",
    "posts/Making this website.md",
    "media/Working Messy with Scribe [Concept] 8c5cf70611c94c579fcd24e95b4cfac7/me.png",
    "media/me.png",
    "projects/buttons-and-switches.md",
    "To dos.md",
    "posts.md",
    "pages/Resume.md",
    "projects.md",
    "media/planner.png",
    "media/Headteacher-Contemporary-Planner-2023-HeadteacherChat-1676483133_8c525786-cc07-45f8-8c9c-99443afdd304.jpg_v=1676483563&width=1100",
    "media/shopify.png",
    "pages/stay-page.md",
    "James Coy e8801d29b2a448f386786c9a4c4d0e0d/Work ddc35f215d7145beba5dde7256965c30/Stay - Hotel Booking App (Concept) 77e75be5ca694cf8ab65f168815dff7b.md",
    "James Coy e8801d29b2a448f386786c9a4c4d0e0d/Work ddc35f215d7145beba5dde7256965c30/HeadteacherChat Mental models and navigation.md"
  ]
}